ocra/orientation/__init__.py
ocra/orientation/best_acc_weights.pth
ocra/orientation/config.json
ocra/orientation/dataset.py
ocra/orientation/generate_rotations_csv.py
ocra/orientation/model.py
ocra/orientation/train.py
ocra/orientation/utils.py
ocra-0.1.4.dist-info/METADATA
ocra-0.1.4.dist-info/WHEEL
ocra-0.1.4.dist-info/top_level.txt
ocra-0.1.4.dist-info/RECORD
