Metadata-Version: 2.4
Name: ocra
Version: 0.1.4
Summary: ocra: toolbox for analyzing text fragments (OrientationPredictor).
License: MIT
Requires-Python: >=3.9
Requires-Dist: torch<3,>=2.0
Requires-Dist: torchvision<0.20,>=0.15
Requires-Dist: timm>=0.9
Requires-Dist: Pillow>=8.0.0
Requires-Dist: tqdm>=4.65
Requires-Dist: numpy<3,>=1.21
